Calculator/__init__.py
Calculator/calculator.py
BahaCalculator-1.0.0.dist-info/LICENSE
BahaCalculator-1.0.0.dist-info/METADATA
BahaCalculator-1.0.0.dist-info/WHEEL
BahaCalculator-1.0.0.dist-info/top_level.txt
BahaCalculator-1.0.0.dist-info/RECORD
