Metadata-Version: 2.1
Name: BahaCalculator
Version: 1.0.0
Summary: Simple calculator
Home-page: https://github.com/p3rc1va1/calculator.git
Author: Baha Celik
Author-email: 35celik.baha@gmail.com
License: MIT
Classifier: Development Status :: 3 - Alpha
Classifier: Intended Audience :: Developers
Classifier: License :: OSI Approved :: MIT License
Classifier: Programming Language :: Python :: 3
Classifier: Programming Language :: Python :: 3.6
Classifier: Programming Language :: Python :: 3.7
Classifier: Programming Language :: Python :: 3.8
Classifier: Programming Language :: Python :: 3.9
License-File: LICENSE
